structlinks/BinaryTree.py
structlinks/DoublyLinkedList.py
structlinks/Graph.py
structlinks/LinkedList.py
structlinks/Matrix.py
structlinks/Queue.py
structlinks/SearchingAlgorithms.py
structlinks/SortingAlgorithms.py
structlinks/Stack.py
structlinks/__init__.py
structlinks/Algorithms/__init__.py
structlinks/Algorithms/SearchingAlgorithms/SearchingAlgorithms.py
structlinks/Algorithms/SearchingAlgorithms/__init__.py
structlinks/Algorithms/SortingAlgorithms/SortingAlgorithms.py
structlinks/Algorithms/SortingAlgorithms/__init__.py
structlinks/DataStructures/__init__.py
structlinks/DataStructures/BinarySearchTree/BinarySearchTree.py
structlinks/DataStructures/BinarySearchTree/__init__.py
structlinks/DataStructures/BinaryTree/BinarySearchTree.py
structlinks/DataStructures/BinaryTree/BinaryTree.py
structlinks/DataStructures/BinaryTree/__init__.py
structlinks/DataStructures/DoublyLinkedList/DoublyLinkedList.py
structlinks/DataStructures/DoublyLinkedList/__init__.py
structlinks/DataStructures/Graph/Graph.py
structlinks/DataStructures/Graph/__init__.py
structlinks/DataStructures/Heap/Heap.py
structlinks/DataStructures/Heap/__init__.py
structlinks/DataStructures/LinkedList/LinkedList.py
structlinks/DataStructures/LinkedList/__init__.py
structlinks/DataStructures/Matrix/Matrix.py
structlinks/DataStructures/Matrix/__init__.py
structlinks/DataStructures/Queue/Queue.py
structlinks/DataStructures/Queue/__init__.py
structlinks/DataStructures/Stack/Stack.py
structlinks/DataStructures/Stack/__init__.py
structlinks-1.1.4.dist-info/LICENSE
structlinks-1.1.4.dist-info/METADATA
structlinks-1.1.4.dist-info/WHEEL
structlinks-1.1.4.dist-info/top_level.txt
structlinks-1.1.4.dist-info/RECORD
