Metadata-Version: 2.1
Name: structlinks
Version: 1.1.4
Summary: Easily access and visualize Data structures
Home-page: https://github.com/eeshannarula29/structlinks
Author: Eeshan Narula
Author-email: eeshannarula29@gmail.com
License: UNKNOWN
Platform: UNKNOWN
Classifier: Programming Language :: Python :: 3
Classifier: License :: OSI Approved :: MIT License
Classifier: Operating System :: OS Independent
Requires-Python: >=3.9.0
